ChangeLog.rst
LICENSE
MANIFEST.in
README.rst
requirements.txt
setup.cfg
setup.py
data/lepidopter-update.py
data/oonideckgen.1
data/ooniprobe-agent.1
data/ooniprobe.1
data/ooniprobe.conf.sample
data/oonireport.1
data/ooniresources.1
data/decks/http-invalid.yaml
data/decks/im.yaml
data/decks/tor.yaml
data/decks/web.yaml
ooni/__init__.py
ooni/backend_client.py
ooni/constants.py
ooni/director.py
ooni/errors.py
ooni/geoip.py
ooni/managers.py
ooni/measurements.py
ooni/nettest.py
ooni/otime.py
ooni/reporter.py
ooni/resources.py
ooni/settings.ini
ooni/settings.py
ooni/tasks.py
ooni/agent/__init__.py
ooni/agent/agent.py
ooni/agent/scheduler.py
ooni/common/__init__.py
ooni/common/http_utils.py
ooni/common/ip_utils.py
ooni/common/tcp_utils.py
ooni/common/txextra.py
ooni/contrib/__init__.py
ooni/contrib/croniter.py
ooni/contrib/dateutil/__init__.py
ooni/contrib/dateutil/relativedelta.py
ooni/contrib/dateutil/tz/__init__.py
ooni/contrib/dateutil/tz/_common.py
ooni/contrib/dateutil/tz/tz.py
ooni/contrib/dateutil/tz/win.py
ooni/deck/__init__.py
ooni/deck/backend.py
ooni/deck/deck.py
ooni/deck/legacy.py
ooni/deck/store.py
ooni/kit/__init__.py
ooni/kit/daphn3.py
ooni/kit/domclass.py
ooni/nettests/__init__.py
ooni/nettests/__init__.pyc
ooni/nettests/blocking/__init__.py
ooni/nettests/blocking/__init__.pyc
ooni/nettests/blocking/bridge_reachability.py
ooni/nettests/blocking/bridge_reachability.pyc
ooni/nettests/blocking/dns_consistency.py
ooni/nettests/blocking/dns_consistency.pyc
ooni/nettests/blocking/dns_n_http.pyc
ooni/nettests/blocking/facebook_messenger.py
ooni/nettests/blocking/facebook_messenger.pyc
ooni/nettests/blocking/http_requests.py
ooni/nettests/blocking/http_requests.pyc
ooni/nettests/blocking/meek_fronted_requests.py
ooni/nettests/blocking/meek_fronted_requests.pyc
ooni/nettests/blocking/tcp_connect.py
ooni/nettests/blocking/tcp_connect.pyc
ooni/nettests/blocking/telegram.py
ooni/nettests/blocking/vanilla_tor.py
ooni/nettests/blocking/vanilla_tor.pyc
ooniprobe.egg-info/PKG-INFO
ooniprobe.egg-info/SOURCES.txt
ooniprobe.egg-info/dependency_links.txt
ooniprobe.egg-info/entry_points.txt
ooniprobe.egg-info/not-zip-safe
ooniprobe.egg-info/requires.txt
ooniprobe.egg-info/top_level.txt